trakos/__init__.py
trakos/my_class.py
trakos-2.0.0.dist-info/LICENSE
trakos-2.0.0.dist-info/METADATA
trakos-2.0.0.dist-info/WHEEL
trakos-2.0.0.dist-info/top_level.txt
trakos-2.0.0.dist-info/RECORD
