Metadata-Version: 2.1
Name: trakos
Version: 2.0.0
Summary: Python Library To Check Websites Users
Home-page: https://github.com/mhdeiiking/trakos
Author: king-trakos
Author-email: trakosiraq@gmail.com
License: UNKNOWN
Project-URL: Bug Tracker, https://github.com/mhdeiiking/trakos/issues
Platform: UNKNOWN
Classifier: Programming Language :: Python :: 3
Classifier: License :: OSI Approved :: MIT License
Classifier: Operating System :: OS Independent
Requires-Python: >=3.9.7
License-File: LICENSE
